examples/__init__.py
examples/main.py
tests/__init__.py
tests/neo4jtest/__init__.py
tests/neo4jtest/graph_data_reader_test.py
twneo/__init__.py
twneo/common/__init__.py
twneo/common/elements/__init__.py
twneo/common/elements/tweet.py
twneo/common/elements/tweet_tag_relation.py
twneo/common/elements/tweet_tweet_relation.py
twneo/common/elements/user.py
twneo/common/elements/user_tweet_relation.py
twneo/config/__init__.py
twneo/config/config.py
twneo/config/config.yaml
twneo/connector/__init__.py
twneo/connector/graph_creator.py
twneo/neo4j/__init__.py
twneo/neo4j/graph_data_reader.py
twneo/neo4j/graph_operations.py
twneo/twitter/__init__.py
twneo/twitter/query_handler.py
twneo/twitter/tweet_collector.py
twneo-0.0.6.dist-info/METADATA
twneo-0.0.6.dist-info/WHEEL
twneo-0.0.6.dist-info/top_level.txt
twneo-0.0.6.dist-info/RECORD
