Metadata-Version: 2.1
Name: twneo
Version: 0.0.6
Summary: uses twitter api to create neo4j graphs
Home-page: https://github.com/pankajti/twneo
Author: Pankaj Kumar
Author-email: kumarp@mail.smu.edu
License: UNKNOWN
Project-URL: Bug Tracker, https://github.com/pankajti/twneo/issues
Platform: UNKNOWN
Classifier: Programming Language :: Python :: 3
Classifier: License :: OSI Approved :: MIT License
Classifier: Operating System :: OS Independent
Requires-Python: >=3.6
